mth5/__init__.py
mth5/helpers.py
mth5/mth5.py
mth5/clients/__init__.py
mth5/clients/base.py
mth5/clients/fdsn.py
mth5/clients/geomag.py
mth5/clients/lemi424.py
mth5/clients/make_mth5.py
mth5/clients/metronix.py
mth5/clients/nims.py
mth5/clients/phoenix.py
mth5/clients/zen.py
mth5/data/1690C16C.TBL
mth5/data/__init__.py
mth5/data/make_mth5_from_asc.py
mth5/data/paths.py
mth5/data/station_config.py
mth5/data/test1.asc
mth5/data/test2.asc
mth5/data/mth5/synthetic_test_data.h5
mth5/groups/__init__.py
mth5/groups/base.py
mth5/groups/channel_dataset.py
mth5/groups/estimate_dataset.py
mth5/groups/experiment.py
mth5/groups/fc_dataset.py
mth5/groups/feature_dataset.py
mth5/groups/features.py
mth5/groups/filters.py
mth5/groups/fourier_coefficients.py
mth5/groups/reports.py
mth5/groups/run.py
mth5/groups/standards.py
mth5/groups/station.py
mth5/groups/survey.py
mth5/groups/transfer_function.py
mth5/groups/filter_groups/__init__.py
mth5/groups/filter_groups/coefficient_filter_group.py
mth5/groups/filter_groups/fap_filter_group.py
mth5/groups/filter_groups/fir_filter_group.py
mth5/groups/filter_groups/time_delay_filter_group.py
mth5/groups/filter_groups/zpk_filter_group.py
mth5/io/__init__.py
mth5/io/collection.py
mth5/io/conversion.py
mth5/io/reader.py
mth5/io/lemi/__init__.py
mth5/io/lemi/lemi424.py
mth5/io/lemi/lemi_collection.py
mth5/io/metronix/__init__.py
mth5/io/metronix/metronix_atss.py
mth5/io/metronix/metronix_collection.py
mth5/io/metronix/metronix_metadata.py
mth5/io/miniseed/__init__.py
mth5/io/miniseed/miniseed.py
mth5/io/nims/__init__.py
mth5/io/nims/gps.py
mth5/io/nims/header.py
mth5/io/nims/nims.py
mth5/io/nims/nims_collection.py
mth5/io/nims/response_filters.py
mth5/io/phoenix/__init__.py
mth5/io/phoenix/phoenix_collection.py
mth5/io/phoenix/read.py
mth5/io/phoenix/readers/__init__.py
mth5/io/phoenix/readers/base.py
mth5/io/phoenix/readers/calibrations.py
mth5/io/phoenix/readers/config.py
mth5/io/phoenix/readers/header.py
mth5/io/phoenix/readers/helpers.py
mth5-0.6.1.dist-info/licenses/LICENSE.md
mth5-0.6.1.dist-info/METADATA
mth5-0.6.1.dist-info/WHEEL
mth5-0.6.1.dist-info/top_level.txt
mth5-0.6.1.dist-info/RECORD
