Metadata-Version: 2.4
Name: mth5
Version: 0.6.1
Summary: Archivable and exchangeable format for magnetotelluric data
Author: Karl Kappler, MTH5 Team
Author-email: Jared Peacock <jpeacock@usgs.gov>
License: MIT
Project-URL: Homepage, https://github.com/kujaku11/mth5
Project-URL: Repository, https://github.com/kujaku11/mth5
Project-URL: Documentation, https://mth5.readthedocs.io/
Project-URL: Bug Tracker, https://github.com/kujaku11/mth5/issues
Keywords: mth5,magnetotellurics,hdf5,data format
Classifier: Development Status :: 5 - Production/Stable
Classifier: Intended Audience :: Developers
Classifier: License :: OSI Approved :: MIT License
Classifier: Natural Language :: English
Classifier: Programming Language :: Python :: 3
Classifier: Programming Language :: Python :: 3.10
Classifier: Programming Language :: Python :: 3.11
Classifier: Programming Language :: Python :: 3.12
Requires-Python: >=3.10
License-File: LICENSE.md
Requires-Dist: h5py
Requires-Dist: pyyaml
Requires-Dist: scipy
Requires-Dist: mt_metadata>=1.0.0
Provides-Extra: obspy
Requires-Dist: obspy; extra == "obspy"
Provides-Extra: test
Requires-Dist: pytest>=3; extra == "test"
Requires-Dist: pytest-xdist; extra == "test"
Requires-Dist: pytest-subtests; extra == "test"
Requires-Dist: pytest-benchmark; extra == "test"
Provides-Extra: dev
Requires-Dist: pytest>=3; extra == "dev"
Requires-Dist: pytest-xdist; extra == "dev"
Requires-Dist: pytest-subtests; extra == "dev"
Requires-Dist: pytest-runner; extra == "dev"
Requires-Dist: pytest-benchmark; extra == "dev"
Requires-Dist: black; extra == "dev"
Requires-Dist: flake8; extra == "dev"
Requires-Dist: isort; extra == "dev"
Requires-Dist: pre-commit; extra == "dev"
Dynamic: license-file
